{
  "fabric:load_conditions": [
    {
      "condition": "fabric:and",
      "values": [
        {
          "condition": "assortedlib:part_enabled",
          "part": "moreshears"
        },
        {
          "condition": "fabric:tags_populated",
          "values": [
            "c:gems/diamond"
          ]
        }
      ]
    }
  ],
  "parent": "minecraft:recipes/root",
  "criteria": {
    "has_item": {
      "conditions": {
        "items": [
          {
            "tag": "c:gems/diamond"
          }
        ]
      },
      "trigger": "minecraft:inventory_changed"
    },
    "has_leather": {
      "conditions": {
        "items": [
          {
            "tag": "c:leather"
          }
        ]
      },
      "trigger": "minecraft:inventory_changed"
    },
    "has_the_recipe": {
      "conditions": {
        "recipe": "assortedtools:diamond_shears"
      },
      "trigger": "minecraft:recipe_unlocked"
    }
  },
  "requirements": [
    [
      "has_leather",
      "has_item",
      "has_the_recipe"
    ]
  ],
  "rewards": {
    "recipes": [
      "assortedtools:diamond_shears"
    ]
  }
}