{
  "fabric:load_conditions": [
    {
      "condition": "fabric:and",
      "values": [
        {
          "condition": "assortedlib:part_enabled",
          "part": "extramaterials"
        },
        {
          "condition": "fabric:tags_populated",
          "values": [
            "c:ingots/invar"
          ]
        }
      ]
    }
  ],
  "type": "minecraft:crafting_shaped",
  "category": "equipment",
  "key": {
    "S": {
      "tag": "c:rods/wooden"
    },
    "X": {
      "tag": "c:ingots/invar"
    }
  },
  "pattern": [
    "XX",
    "SX",
    "S "
  ],
  "result": {
    "item": "assortedtools:invar_axe"
  },
  "show_notification": true
}