{
  "type": "forge:conditional",
  "recipes": [
    {
      "conditions": [
        {
          "type": "assortedtools:part_enabled",
          "part": "moreshears"
        },
        {
          "type": "forge:not",
          "value": {
            "type": "forge:tag_empty",
            "tag": "forge:gems/diamond"
          }
        }
      ],
      "recipe": {
        "type": "minecraft:crafting_shaped",
        "key": {
          "I": {
            "tag": "forge:gems/diamond"
          },
          "L": {
            "tag": "forge:leather"
          }
        },
        "pattern": [
          "LI",
          "I "
        ],
        "result": {
          "item": "assortedtools:diamond_shears"
        }
      }
    }
  ]
}