{
  "type": "forge:conditional",
  "recipes": [
    {
      "conditions": [
        {
          "part": "multitools",
          "type": "assortedtools:part_enabled"
        }
      ],
      "recipe": {
        "type": "minecraft:crafting_shapeless",
        "ingredients": [
          {
            "tag": "forge:swords/stone"
          },
          {
            "tag": "forge:pickaxes/stone"
          },
          {
            "tag": "forge:shovels/stone"
          },
          {
            "tag": "forge:hoes/stone"
          },
          {
            "tag": "forge:axes/stone"
          },
          {
            "tag": "forge:cobblestone"
          },
          {
            "tag": "forge:cobblestone"
          },
          {
            "tag": "forge:cobblestone"
          },
          {
            "tag": "forge:cobblestone"
          }
        ],
        "result": {
          "item": "assortedtools:stone_multitool"
        }
      }
    }
  ]
}