{
  "parent": "minecraft:recipes/root",
  "rewards": {
    "recipes": [
      "assortedtools:diamond_boomerang"
    ]
  },
  "criteria": {
    "has_diamonds": {
      "trigger": "minecraft:inventory_changed",
      "conditions": {
        "items": [
          {
            "tag": "forge:gems/diamond"
          }
        ]
      }
    },
    "has_the_recipe": {
      "trigger": "minecraft:recipe_unlocked",
      "conditions": {
        "recipe": "assortedtools:diamond_boomerang"
      }
    }
  },
  "requirements": [
    [
      "has_diamonds",
      "has_the_recipe"
    ]
  ]
}