{
  "advancements": [
    {
      "advancement": {
        "parent": "minecraft:recipes/root",
        "criteria": {
          "has_item": {
            "conditions": {
              "items": [
                {
                  "tag": "forge:ingots/invar"
                }
              ]
            },
            "trigger": "minecraft:inventory_changed"
          },
          "has_leather": {
            "conditions": {
              "items": [
                {
                  "tag": "forge:leather"
                }
              ]
            },
            "trigger": "minecraft:inventory_changed"
          },
          "has_the_recipe": {
            "conditions": {
              "recipe": "assortedtools:invar_shears"
            },
            "trigger": "minecraft:recipe_unlocked"
          }
        },
        "requirements": [
          [
            "has_leather",
            "has_item",
            "has_the_recipe"
          ]
        ],
        "rewards": {
          "recipes": [
            "assortedtools:invar_shears"
          ]
        }
      },
      "conditions": [
        {
          "type": "assortedtools:part_enabled",
          "part": "moreshears"
        },
        {
          "type": "forge:not",
          "value": {
            "type": "forge:tag_empty",
            "tag": "forge:ingots/invar"
          }
        },
        {
          "type": "assortedtools:part_enabled",
          "part": "extramaterials"
        }
      ]
    }
  ]
}